webinar/__init__.py
webinar/main.py
webinar-0.2.dist-info/LICENSE
webinar-0.2.dist-info/METADATA
webinar-0.2.dist-info/WHEEL
webinar-0.2.dist-info/entry_points.txt
webinar-0.2.dist-info/top_level.txt
webinar-0.2.dist-info/RECORD
