Metadata-Version: 2.1
Name: webinar
Version: 0.2
Summary: A webinar bot package
Home-page: https://github.com/emhayusa/webinar
Author: Muhammad Hasannudin Yusa
Author-email: emhayusa@gmail.com
License: UNKNOWN
Platform: UNKNOWN
Classifier: Programming Language :: Python :: 3
Classifier: License :: OSI Approved :: MIT License
Classifier: Operating System :: OS Independent
Requires-Dist: Click
